[
  {
    "id": 105306,
    "name": "AMPHOE CHON DAEN",
    "state": "PHETCHABUN",
    "state_iso2": "67",
    "country": "THAILAND",
    "country_iso2": "TH",
    "country_iso3": "THA",
    "country_native": "ประเทศไทย"
  },
  {
    "id": 105493,
    "name": "AMPHOE LOM SAK",
    "state": "PHETCHABUN",
    "state_iso2": "67",
    "country": "THAILAND",
    "country_iso2": "TH",
    "country_iso3": "THA",
    "country_native": "ประเทศไทย"
  },
  {
    "id": 105675,
    "name": "AMPHOE NONG PHAI",
    "state": "PHETCHABUN",
    "state_iso2": "67",
    "country": "THAILAND",
    "country_iso2": "TH",
    "country_iso3": "THA",
    "country_native": "ประเทศไทย"
  },
  {
    "id": 106368,
    "name": "AMPHOE WICHIAN BURI",
    "state": "PHETCHABUN",
    "state_iso2": "67",
    "country": "THAILAND",
    "country_iso2": "TH",
    "country_iso3": "THA",
    "country_native": "ประเทศไทย"
  },
  {
    "id": 105262,
    "name": "BUENG SAM PHAN",
    "state": "PHETCHABUN",
    "state_iso2": "67",
    "country": "THAILAND",
    "country_iso2": "TH",
    "country_iso3": "THA",
    "country_native": "ประเทศไทย"
  },
  {
    "id": 106482,
    "name": "CHON DAEN",
    "state": "PHETCHABUN",
    "state_iso2": "67",
    "country": "THAILAND",
    "country_iso2": "TH",
    "country_iso3": "THA",
    "country_native": "ประเทศไทย"
  },
  {
    "id": 105395,
    "name": "KHAO KHO",
    "state": "PHETCHABUN",
    "state_iso2": "67",
    "country": "THAILAND",
    "country_iso2": "TH",
    "country_iso3": "THA",
    "country_native": "ประเทศไทย"
  },
  {
    "id": 105492,
    "name": "LOM KAO",
    "state": "PHETCHABUN",
    "state_iso2": "67",
    "country": "THAILAND",
    "country_iso2": "TH",
    "country_iso3": "THA",
    "country_native": "ประเทศไทย"
  },
  {
    "id": 106558,
    "name": "LOM SAK",
    "state": "PHETCHABUN",
    "state_iso2": "67",
    "country": "THAILAND",
    "country_iso2": "TH",
    "country_iso3": "THA",
    "country_native": "ประเทศไทย"
  },
  {
    "id": 105570,
    "name": "MUEANG PHETCHABUN",
    "state": "PHETCHABUN",
    "state_iso2": "67",
    "country": "THAILAND",
    "country_iso2": "TH",
    "country_iso3": "THA",
    "country_native": "ประเทศไทย"
  },
  {
    "id": 105636,
    "name": "NAM NAO",
    "state": "PHETCHABUN",
    "state_iso2": "67",
    "country": "THAILAND",
    "country_iso2": "TH",
    "country_iso3": "THA",
    "country_native": "ประเทศไทย"
  },
  {
    "id": 106603,
    "name": "NONG PHAI",
    "state": "PHETCHABUN",
    "state_iso2": "67",
    "country": "THAILAND",
    "country_iso2": "TH",
    "country_iso3": "THA",
    "country_native": "ประเทศไทย"
  },
  {
    "id": 106631,
    "name": "PHETCHABUN",
    "state": "PHETCHABUN",
    "state_iso2": "67",
    "country": "THAILAND",
    "country_iso2": "TH",
    "country_iso3": "THA",
    "country_native": "ประเทศไทย"
  },
  {
    "id": 106229,
    "name": "SI THEP",
    "state": "PHETCHABUN",
    "state_iso2": "67",
    "country": "THAILAND",
    "country_iso2": "TH",
    "country_iso3": "THA",
    "country_native": "ประเทศไทย"
  },
  {
    "id": 106343,
    "name": "WANG PONG",
    "state": "PHETCHABUN",
    "state_iso2": "67",
    "country": "THAILAND",
    "country_iso2": "TH",
    "country_iso3": "THA",
    "country_native": "ประเทศไทย"
  },
  {
    "id": 106752,
    "name": "WICHIAN BURI",
    "state": "PHETCHABUN",
    "state_iso2": "67",
    "country": "THAILAND",
    "country_iso2": "TH",
    "country_iso3": "THA",
    "country_native": "ประเทศไทย"
  }
]