[
  {
    "id": 104796,
    "name": "GAALKACYO",
    "state": "MUDUG",
    "state_iso2": "MU",
    "country": "SOMALIA",
    "country_iso2": "SO",
    "country_iso3": "SOM",
    "country_native": "SOOMAALIYA"
  },
  {
    "id": 104799,
    "name": "HOBYO",
    "state": "MUDUG",
    "state_iso2": "MU",
    "country": "SOMALIA",
    "country_iso2": "SO",
    "country_iso3": "SOM",
    "country_native": "SOOMAALIYA"
  },
  {
    "id": 104818,
    "name": "XARARDHEERE",
    "state": "MUDUG",
    "state_iso2": "MU",
    "country": "SOMALIA",
    "country_iso2": "SO",
    "country_iso3": "SOM",
    "country_native": "SOOMAALIYA"
  }
]