[
  {
    "id": 107264,
    "name": "BAHŞILI",
    "state": "KIRIKKALE",
    "state_iso2": "71",
    "country": "TURKEY",
    "country_iso2": "TR",
    "country_iso3": "TUR",
    "country_native": "TÜRKIYE"
  },
  {
    "id": 107279,
    "name": "BALIŞEYH",
    "state": "KIRIKKALE",
    "state_iso2": "71",
    "country": "TURKEY",
    "country_iso2": "TR",
    "country_iso3": "TUR",
    "country_native": "TÜRKIYE"
  },
  {
    "id": 107459,
    "name": "DELICE",
    "state": "KIRIKKALE",
    "state_iso2": "71",
    "country": "TURKEY",
    "country_iso2": "TR",
    "country_iso3": "TUR",
    "country_native": "TÜRKIYE"
  },
  {
    "id": 107897,
    "name": "KARAKEÇILI",
    "state": "KIRIKKALE",
    "state_iso2": "71",
    "country": "TURKEY",
    "country_iso2": "TR",
    "country_iso3": "TUR",
    "country_native": "TÜRKIYE"
  },
  {
    "id": 107985,
    "name": "KESKIN",
    "state": "KIRIKKALE",
    "state_iso2": "71",
    "country": "TURKEY",
    "country_iso2": "TR",
    "country_iso3": "TUR",
    "country_native": "TÜRKIYE"
  },
  {
    "id": 108109,
    "name": "MERKEZ",
    "state": "KIRIKKALE",
    "state_iso2": "71",
    "country": "TURKEY",
    "country_iso2": "TR",
    "country_iso3": "TUR",
    "country_native": "TÜRKIYE"
  },
  {
    "id": 108490,
    "name": "SULAKYURT",
    "state": "KIRIKKALE",
    "state_iso2": "71",
    "country": "TURKEY",
    "country_iso2": "TR",
    "country_iso3": "TUR",
    "country_native": "TÜRKIYE"
  },
  {
    "id": 108659,
    "name": "YAHŞIHAN",
    "state": "KIRIKKALE",
    "state_iso2": "71",
    "country": "TURKEY",
    "country_iso2": "TR",
    "country_iso3": "TUR",
    "country_native": "TÜRKIYE"
  },
  {
    "id": 108813,
    "name": "ÇELEBI",
    "state": "KIRIKKALE",
    "state_iso2": "71",
    "country": "TURKEY",
    "country_iso2": "TR",
    "country_iso3": "TUR",
    "country_native": "TÜRKIYE"
  }
]