[
  {
    "id": 104940,
    "name": "AD DARBĀSĪYAH",
    "state": "AL-HASAKAH",
    "state_iso2": "HA",
    "country": "SYRIA",
    "country_iso2": "SY",
    "country_iso3": "SYR",
    "country_native": "سوريا"
  },
  {
    "id": 104950,
    "name": "AL MĀLIKĪYAH",
    "state": "AL-HASAKAH",
    "state_iso2": "HA",
    "country": "SYRIA",
    "country_iso2": "SY",
    "country_iso3": "SYR",
    "country_native": "سوريا"
  },
  {
    "id": 104955,
    "name": "AL QĀMISHLĪ",
    "state": "AL-HASAKAH",
    "state_iso2": "HA",
    "country": "SYRIA",
    "country_iso2": "SY",
    "country_iso3": "SYR",
    "country_native": "سوريا"
  },
  {
    "id": 104957,
    "name": "AL ḨASAKAH",
    "state": "AL-HASAKAH",
    "state_iso2": "HA",
    "country": "SYRIA",
    "country_iso2": "SY",
    "country_iso3": "SYR",
    "country_native": "سوريا"
  },
  {
    "id": 104960,
    "name": "AL-MALIKIYAH",
    "state": "AL-HASAKAH",
    "state_iso2": "HA",
    "country": "SYRIA",
    "country_iso2": "SY",
    "country_iso3": "SYR",
    "country_native": "سوريا"
  },
  {
    "id": 104967,
    "name": "AMUDE",
    "state": "AL-HASAKAH",
    "state_iso2": "HA",
    "country": "SYRIA",
    "country_iso2": "SY",
    "country_iso3": "SYR",
    "country_native": "سوريا"
  }
]