[
  {
    "id": 104787,
    "name": "CADALE",
    "state": "MIDDLE SHEBELLE",
    "state_iso2": "SD",
    "country": "SOMALIA",
    "country_iso2": "SO",
    "country_iso3": "SOM",
    "country_native": "SOOMAALIYA"
  },
  {
    "id": 104803,
    "name": "JAWHAR",
    "state": "MIDDLE SHEBELLE",
    "state_iso2": "SD",
    "country": "SOMALIA",
    "country_iso2": "SO",
    "country_iso3": "SOM",
    "country_native": "SOOMAALIYA"
  },
  {
    "id": 104808,
    "name": "MAHADDAYWEYNE",
    "state": "MIDDLE SHEBELLE",
    "state_iso2": "SD",
    "country": "SOMALIA",
    "country_iso2": "SO",
    "country_iso3": "SOM",
    "country_native": "SOOMAALIYA"
  }
]