[
  {
    "id": 1917,
    "name": "BA",
    "iso2": "01",
    "country": "FIJI ISLANDS",
    "country_iso2": "FJ",
    "country_iso3": "FJI",
    "country_native": "FIJI",
    "timezone": "Pacific/Fiji"
  },
  {
    "id": 1930,
    "name": "BUA",
    "iso2": "02",
    "country": "FIJI ISLANDS",
    "country_iso2": "FJ",
    "country_iso3": "FJI",
    "country_native": "FIJI",
    "timezone": "Pacific/Fiji"
  },
  {
    "id": 1924,
    "name": "CAKAUDROVE",
    "iso2": "03",
    "country": "FIJI ISLANDS",
    "country_iso2": "FJ",
    "country_iso3": "FJI",
    "country_native": "FIJI",
    "timezone": "Pacific/Fiji"
  },
  {
    "id": 1929,
    "name": "CENTRAL",
    "iso2": "C",
    "country": "FIJI ISLANDS",
    "country_iso2": "FJ",
    "country_iso3": "FJI",
    "country_native": "FIJI",
    "timezone": "Pacific/Fiji"
  },
  {
    "id": 1932,
    "name": "EASTERN",
    "iso2": "E",
    "country": "FIJI ISLANDS",
    "country_iso2": "FJ",
    "country_iso3": "FJI",
    "country_native": "FIJI",
    "timezone": "Pacific/Fiji"
  },
  {
    "id": 1934,
    "name": "KADAVU",
    "iso2": "04",
    "country": "FIJI ISLANDS",
    "country_iso2": "FJ",
    "country_iso3": "FJI",
    "country_native": "FIJI",
    "timezone": "Pacific/Fiji"
  },
  {
    "id": 1933,
    "name": "LAU",
    "iso2": "05",
    "country": "FIJI ISLANDS",
    "country_iso2": "FJ",
    "country_iso3": "FJI",
    "country_native": "FIJI",
    "timezone": "Pacific/Fiji"
  },
  {
    "id": 1916,
    "name": "LOMAIVITI",
    "iso2": "06",
    "country": "FIJI ISLANDS",
    "country_iso2": "FJ",
    "country_iso3": "FJI",
    "country_native": "FIJI",
    "timezone": "Pacific/Fiji"
  },
  {
    "id": 1922,
    "name": "MACUATA",
    "iso2": "07",
    "country": "FIJI ISLANDS",
    "country_iso2": "FJ",
    "country_iso3": "FJI",
    "country_native": "FIJI",
    "timezone": "Pacific/Fiji"
  },
  {
    "id": 1919,
    "name": "NADROGA-NAVOSA",
    "iso2": "08",
    "country": "FIJI ISLANDS",
    "country_iso2": "FJ",
    "country_iso3": "FJI",
    "country_native": "FIJI",
    "timezone": "Pacific/Fiji"
  },
  {
    "id": 1927,
    "name": "NAITASIRI",
    "iso2": "09",
    "country": "FIJI ISLANDS",
    "country_iso2": "FJ",
    "country_iso3": "FJI",
    "country_native": "FIJI",
    "timezone": "Pacific/Fiji"
  },
  {
    "id": 1928,
    "name": "NAMOSI",
    "iso2": "10",
    "country": "FIJI ISLANDS",
    "country_iso2": "FJ",
    "country_iso3": "FJI",
    "country_native": "FIJI",
    "timezone": "Pacific/Fiji"
  },
  {
    "id": 1921,
    "name": "NORTHERN",
    "iso2": "N",
    "country": "FIJI ISLANDS",
    "country_iso2": "FJ",
    "country_iso3": "FJI",
    "country_native": "FIJI",
    "timezone": "Pacific/Fiji"
  },
  {
    "id": 1926,
    "name": "RA",
    "iso2": "11",
    "country": "FIJI ISLANDS",
    "country_iso2": "FJ",
    "country_iso3": "FJI",
    "country_native": "FIJI",
    "timezone": "Pacific/Fiji"
  },
  {
    "id": 1920,
    "name": "REWA",
    "iso2": "12",
    "country": "FIJI ISLANDS",
    "country_iso2": "FJ",
    "country_iso3": "FJI",
    "country_native": "FIJI",
    "timezone": "Pacific/Fiji"
  },
  {
    "id": 1931,
    "name": "ROTUMA",
    "iso2": "R",
    "country": "FIJI ISLANDS",
    "country_iso2": "FJ",
    "country_iso3": "FJI",
    "country_native": "FIJI",
    "timezone": "Pacific/Fiji"
  },
  {
    "id": 1925,
    "name": "SERUA",
    "iso2": "13",
    "country": "FIJI ISLANDS",
    "country_iso2": "FJ",
    "country_iso3": "FJI",
    "country_native": "FIJI",
    "timezone": "Pacific/Fiji"
  },
  {
    "id": 1918,
    "name": "TAILEVU",
    "iso2": "14",
    "country": "FIJI ISLANDS",
    "country_iso2": "FJ",
    "country_iso3": "FJI",
    "country_native": "FIJI",
    "timezone": "Pacific/Fiji"
  },
  {
    "id": 1923,
    "name": "WESTERN",
    "iso2": "W",
    "country": "FIJI ISLANDS",
    "country_iso2": "FJ",
    "country_iso3": "FJI",
    "country_native": "FIJI",
    "timezone": "Pacific/Fiji"
  }
]