[
  {
    "id": 66877,
    "name": "AUCE",
    "state": "DOBELE",
    "state_iso2": "026",
    "country": "LATVIA",
    "country_iso2": "LV",
    "country_iso3": "LVA",
    "country_native": "LATVIJA"
  },
  {
    "id": 66892,
    "name": "DOBELE",
    "state": "DOBELE",
    "state_iso2": "026",
    "country": "LATVIA",
    "country_iso2": "LV",
    "country_iso3": "LVA",
    "country_native": "LATVIJA"
  },
  {
    "id": 66972,
    "name": "TĒRVETE",
    "state": "DOBELE",
    "state_iso2": "026",
    "country": "LATVIA",
    "country_iso2": "LV",
    "country_iso3": "LVA",
    "country_native": "LATVIJA"
  },
  {
    "id": 66988,
    "name": "ZELMEŅI",
    "state": "DOBELE",
    "state_iso2": "026",
    "country": "LATVIA",
    "country_iso2": "LV",
    "country_iso3": "LVA",
    "country_native": "LATVIJA"
  }
]