[
  {
    "id": 9254,
    "name": "ANTON",
    "state": "SOFIA",
    "state_iso2": "23",
    "country": "BULGARIA",
    "country_iso2": "BG",
    "country_iso3": "BGR",
    "country_native": "БЪЛГАРИЯ"
  },
  {
    "id": 9282,
    "name": "BOTEVGRAD",
    "state": "SOFIA",
    "state_iso2": "23",
    "country": "BULGARIA",
    "country_iso2": "BG",
    "country_iso3": "BGR",
    "country_native": "БЪЛГАРИЯ"
  },
  {
    "id": 9285,
    "name": "BOZHURISHTE",
    "state": "SOFIA",
    "state_iso2": "23",
    "country": "BULGARIA",
    "country_iso2": "BG",
    "country_iso3": "BGR",
    "country_native": "БЪЛГАРИЯ"
  },
  {
    "id": 9296,
    "name": "CHAVDAR",
    "state": "SOFIA",
    "state_iso2": "23",
    "country": "BULGARIA",
    "country_iso2": "BG",
    "country_iso3": "BGR",
    "country_native": "БЪЛГАРИЯ"
  },
  {
    "id": 9297,
    "name": "CHELOPECH",
    "state": "SOFIA",
    "state_iso2": "23",
    "country": "BULGARIA",
    "country_iso2": "BG",
    "country_iso3": "BGR",
    "country_native": "БЪЛГАРИЯ"
  },
  {
    "id": 9311,
    "name": "DOLNA BANYA",
    "state": "SOFIA",
    "state_iso2": "23",
    "country": "BULGARIA",
    "country_iso2": "BG",
    "country_iso3": "BGR",
    "country_native": "БЪЛГАРИЯ"
  },
  {
    "id": 9316,
    "name": "DRAGOMAN",
    "state": "SOFIA",
    "state_iso2": "23",
    "country": "BULGARIA",
    "country_iso2": "BG",
    "country_iso3": "BGR",
    "country_native": "БЪЛГАРИЯ"
  },
  {
    "id": 9326,
    "name": "ELIN PELIN",
    "state": "SOFIA",
    "state_iso2": "23",
    "country": "BULGARIA",
    "country_iso2": "BG",
    "country_iso3": "BGR",
    "country_native": "БЪЛГАРИЯ"
  },
  {
    "id": 9327,
    "name": "ETROPOLE",
    "state": "SOFIA",
    "state_iso2": "23",
    "country": "BULGARIA",
    "country_iso2": "BG",
    "country_iso3": "BGR",
    "country_native": "БЪЛГАРИЯ"
  },
  {
    "id": 9332,
    "name": "GODECH",
    "state": "SOFIA",
    "state_iso2": "23",
    "country": "BULGARIA",
    "country_iso2": "BG",
    "country_iso3": "BGR",
    "country_native": "БЪЛГАРИЯ"
  },
  {
    "id": 9333,
    "name": "GORNA MALINA",
    "state": "SOFIA",
    "state_iso2": "23",
    "country": "BULGARIA",
    "country_iso2": "BG",
    "country_iso3": "BGR",
    "country_native": "БЪЛГАРИЯ"
  },
  {
    "id": 9346,
    "name": "IHTIMAN",
    "state": "SOFIA",
    "state_iso2": "23",
    "country": "BULGARIA",
    "country_iso2": "BG",
    "country_iso3": "BGR",
    "country_native": "БЪЛГАРИЯ"
  },
  {
    "id": 9369,
    "name": "KOPRIVSHTITSA",
    "state": "SOFIA",
    "state_iso2": "23",
    "country": "BULGARIA",
    "country_iso2": "BG",
    "country_iso3": "BGR",
    "country_native": "БЪЛГАРИЯ"
  },
  {
    "id": 9370,
    "name": "KOSTINBROD",
    "state": "SOFIA",
    "state_iso2": "23",
    "country": "BULGARIA",
    "country_iso2": "BG",
    "country_iso3": "BGR",
    "country_native": "БЪЛГАРИЯ"
  },
  {
    "id": 9382,
    "name": "LAKATNIK",
    "state": "SOFIA",
    "state_iso2": "23",
    "country": "BULGARIA",
    "country_iso2": "BG",
    "country_iso3": "BGR",
    "country_native": "БЪЛГАРИЯ"
  },
  {
    "id": 9402,
    "name": "MIRKOVO",
    "state": "SOFIA",
    "state_iso2": "23",
    "country": "BULGARIA",
    "country_iso2": "BG",
    "country_iso3": "BGR",
    "country_native": "БЪЛГАРИЯ"
  },
  {
    "id": 9414,
    "name": "OBSHTINA ANTON",
    "state": "SOFIA",
    "state_iso2": "23",
    "country": "BULGARIA",
    "country_iso2": "BG",
    "country_iso3": "BGR",
    "country_native": "БЪЛГАРИЯ"
  },
  {
    "id": 9436,
    "name": "OBSHTINA BOTEVGRAD",
    "state": "SOFIA",
    "state_iso2": "23",
    "country": "BULGARIA",
    "country_iso2": "BG",
    "country_iso3": "BGR",
    "country_native": "БЪЛГАРИЯ"
  },
  {
    "id": 9439,
    "name": "OBSHTINA BOZHURISHTE",
    "state": "SOFIA",
    "state_iso2": "23",
    "country": "BULGARIA",
    "country_iso2": "BG",
    "country_iso3": "BGR",
    "country_native": "БЪЛГАРИЯ"
  },
  {
    "id": 9445,
    "name": "OBSHTINA CHAVDAR",
    "state": "SOFIA",
    "state_iso2": "23",
    "country": "BULGARIA",
    "country_iso2": "BG",
    "country_iso3": "BGR",
    "country_native": "БЪЛГАРИЯ"
  },
  {
    "id": 9446,
    "name": "OBSHTINA CHELOPECH",
    "state": "SOFIA",
    "state_iso2": "23",
    "country": "BULGARIA",
    "country_iso2": "BG",
    "country_iso3": "BGR",
    "country_native": "БЪЛГАРИЯ"
  },
  {
    "id": 9459,
    "name": "OBSHTINA DOLNA BANYA",
    "state": "SOFIA",
    "state_iso2": "23",
    "country": "BULGARIA",
    "country_iso2": "BG",
    "country_iso3": "BGR",
    "country_native": "БЪЛГАРИЯ"
  },
  {
    "id": 9464,
    "name": "OBSHTINA DRAGOMAN",
    "state": "SOFIA",
    "state_iso2": "23",
    "country": "BULGARIA",
    "country_iso2": "BG",
    "country_iso3": "BGR",
    "country_native": "БЪЛГАРИЯ"
  },
  {
    "id": 9472,
    "name": "OBSHTINA ELIN PELIN",
    "state": "SOFIA",
    "state_iso2": "23",
    "country": "BULGARIA",
    "country_iso2": "BG",
    "country_iso3": "BGR",
    "country_native": "БЪЛГАРИЯ"
  },
  {
    "id": 9473,
    "name": "OBSHTINA ETROPOLE",
    "state": "SOFIA",
    "state_iso2": "23",
    "country": "BULGARIA",
    "country_iso2": "BG",
    "country_iso3": "BGR",
    "country_native": "БЪЛГАРИЯ"
  },
  {
    "id": 9480,
    "name": "OBSHTINA GORNA MALINA",
    "state": "SOFIA",
    "state_iso2": "23",
    "country": "BULGARIA",
    "country_iso2": "BG",
    "country_iso3": "BGR",
    "country_native": "БЪЛГАРИЯ"
  },
  {
    "id": 9505,
    "name": "OBSHTINA KOPRIVSHTITSA",
    "state": "SOFIA",
    "state_iso2": "23",
    "country": "BULGARIA",
    "country_iso2": "BG",
    "country_iso3": "BGR",
    "country_native": "БЪЛГАРИЯ"
  },
  {
    "id": 9506,
    "name": "OBSHTINA KOSTENETS",
    "state": "SOFIA",
    "state_iso2": "23",
    "country": "BULGARIA",
    "country_iso2": "BG",
    "country_iso3": "BGR",
    "country_native": "БЪЛГАРИЯ"
  },
  {
    "id": 9507,
    "name": "OBSHTINA KOSTINBROD",
    "state": "SOFIA",
    "state_iso2": "23",
    "country": "BULGARIA",
    "country_iso2": "BG",
    "country_iso3": "BGR",
    "country_native": "БЪЛГАРИЯ"
  },
  {
    "id": 9533,
    "name": "OBSHTINA MIRKOVO",
    "state": "SOFIA",
    "state_iso2": "23",
    "country": "BULGARIA",
    "country_iso2": "BG",
    "country_iso3": "BGR",
    "country_native": "БЪЛГАРИЯ"
  },
  {
    "id": 9556,
    "name": "OBSHTINA PIRDOP",
    "state": "SOFIA",
    "state_iso2": "23",
    "country": "BULGARIA",
    "country_iso2": "BG",
    "country_iso3": "BGR",
    "country_native": "БЪЛГАРИЯ"
  },
  {
    "id": 9563,
    "name": "OBSHTINA PRAVETS",
    "state": "SOFIA",
    "state_iso2": "23",
    "country": "BULGARIA",
    "country_iso2": "BG",
    "country_iso3": "BGR",
    "country_native": "БЪЛГАРИЯ"
  },
  {
    "id": 9580,
    "name": "OBSHTINA SAMOKOV",
    "state": "SOFIA",
    "state_iso2": "23",
    "country": "BULGARIA",
    "country_iso2": "BG",
    "country_iso3": "BGR",
    "country_native": "БЪЛГАРИЯ"
  },
  {
    "id": 9592,
    "name": "OBSHTINA SLIVNITSA",
    "state": "SOFIA",
    "state_iso2": "23",
    "country": "BULGARIA",
    "country_iso2": "BG",
    "country_iso3": "BGR",
    "country_native": "БЪЛГАРИЯ"
  },
  {
    "id": 9609,
    "name": "OBSHTINA SVOGE",
    "state": "SOFIA",
    "state_iso2": "23",
    "country": "BULGARIA",
    "country_iso2": "BG",
    "country_iso3": "BGR",
    "country_native": "БЪЛГАРИЯ"
  },
  {
    "id": 9638,
    "name": "OBSHTINA ZLATITSA",
    "state": "SOFIA",
    "state_iso2": "23",
    "country": "BULGARIA",
    "country_iso2": "BG",
    "country_iso3": "BGR",
    "country_native": "БЪЛГАРИЯ"
  },
  {
    "id": 9654,
    "name": "PIRDOP",
    "state": "SOFIA",
    "state_iso2": "23",
    "country": "BULGARIA",
    "country_iso2": "BG",
    "country_iso3": "BGR",
    "country_native": "БЪЛГАРИЯ"
  },
  {
    "id": 9661,
    "name": "PRAVETS",
    "state": "SOFIA",
    "state_iso2": "23",
    "country": "BULGARIA",
    "country_iso2": "BG",
    "country_iso3": "BGR",
    "country_native": "БЪЛГАРИЯ"
  },
  {
    "id": 9679,
    "name": "SAMOKOV",
    "state": "SOFIA",
    "state_iso2": "23",
    "country": "BULGARIA",
    "country_iso2": "BG",
    "country_iso3": "BGR",
    "country_native": "БЪЛГАРИЯ"
  },
  {
    "id": 9698,
    "name": "SLIVNITSA",
    "state": "SOFIA",
    "state_iso2": "23",
    "country": "BULGARIA",
    "country_iso2": "BG",
    "country_iso3": "BGR",
    "country_native": "БЪЛГАРИЯ"
  },
  {
    "id": 9718,
    "name": "SVOGE",
    "state": "SOFIA",
    "state_iso2": "23",
    "country": "BULGARIA",
    "country_iso2": "BG",
    "country_iso3": "BGR",
    "country_native": "БЪЛГАРИЯ"
  },
  {
    "id": 9750,
    "name": "ZLATITSA",
    "state": "SOFIA",
    "state_iso2": "23",
    "country": "BULGARIA",
    "country_iso2": "BG",
    "country_iso3": "BGR",
    "country_native": "БЪЛГАРИЯ"
  }
]